{
  "title": "Languages I work with",
  "languages": [
    { "name": "TypeScript", "percent": 20, "color": "#3178c6" },
    { "name": "C#", "percent": 18, "color": "#178600" },
    { "name": "Rust", "percent": 16, "color": "#dea584" },
    { "name": "Python", "percent": 14, "color": "#3572A5" },
    { "name": "JavaScript", "percent": 12, "color": "#f1e05a" },
    { "name": "C++", "percent": 10, "color": "#f34b7d" },
    { "name": "HTML", "percent": 5, "color": "#e34c26" },
    { "name": "CSS", "percent": 3, "color": "#663399" },
    { "name": "PowerShell", "percent": 2, "color": "#012456" }
  ]
}
